<?xml version="1.0" encoding="UTF-8" standalone="yes"?>
<IndivoDocuments>
	<BloodPressureAdherenceItem>
		<name>FORA D40b</name>
		<reportedBy>rpoole@records.media.mit.edu</reportedBy>
		<dateReported>2010-01-15T14:57:00Z</dateReported>
		<adherence>true</adherence>
		<systolic>118</systolic>
		<diastolic>78</diastolic>
		<heartRate>78</heartRate>
	</BloodPressureAdherenceItem>
	<BloodPressureAdherenceItem>
		<name>FORA D40b</name>
		<reportedBy>rpoole@records.media.mit.edu</reportedBy>
		<dateReported>2010-01-16T13:07:00Z</dateReported>
		<adherence>true</adherence>
		<systolic>116</systolic>
		<diastolic>73</diastolic>
		<heartRate>72</heartRate>
	</BloodPressureAdherenceItem>
	<BloodPressureAdherenceItem>
		<name>FORA D40b</name>
		<reportedBy>rpoole@records.media.mit.edu</reportedBy>
		<dateReported>2010-01-17T13:54:00Z</dateReported>
		<adherence>true</adherence>
		<systolic>115</systolic>
		<diastolic>75</diastolic>
		<heartRate>75</heartRate>
	</BloodPressureAdherenceItem>
	<BloodPressureAdherenceItem>
		<name>FORA D40b</name>
		<reportedBy>rpoole@records.media.mit.edu</reportedBy>
		<dateReported>2010-01-18T13:52:00Z</dateReported>
		<adherence>true</adherence>
		<systolic>129</systolic>
		<diastolic>82</diastolic>
		<heartRate>70</heartRate>
	</BloodPressureAdherenceItem>
	<BloodPressureAdherenceItem>
		<name>FORA D40b</name>
		<reportedBy>rpoole@records.media.mit.edu</reportedBy>
		<dateReported>2010-01-19T13:48:00Z</dateReported>
		<adherence>true</adherence>
		<systolic>141</systolic>
		<diastolic>90</diastolic>
		<heartRate>69</heartRate>
	</BloodPressureAdherenceItem>
	<BloodPressureAdherenceItem>
		<name>FORA D40b</name>
		<reportedBy>rpoole@records.media.mit.edu</reportedBy>
		<dateReported>2010-01-20T14:27:00Z</dateReported>
		<adherence>true</adherence>
		<systolic>139</systolic>
		<diastolic>92</diastolic>
		<heartRate>68</heartRate>
	</BloodPressureAdherenceItem>
	<BloodPressureAdherenceItem>
		<name>FORA D40b</name>
		<reportedBy>rpoole@records.media.mit.edu</reportedBy>
		<dateReported>2010-01-21T14:24:00Z</dateReported>
		<adherence>true</adherence>
		<systolic>126</systolic>
		<diastolic>85</diastolic>
		<heartRate>68</heartRate>
	</BloodPressureAdherenceItem>
	<BloodPressureAdherenceItem>
		<name>FORA D40b</name>
		<reportedBy>rpoole@records.media.mit.edu</reportedBy>
		<dateReported>2010-01-22T14:14:00Z</dateReported>
		<adherence>true</adherence>
		<systolic>120</systolic>
		<diastolic>79</diastolic>
		<heartRate>75</heartRate>
	</BloodPressureAdherenceItem>
	<BloodPressureAdherenceItem>
		<name>FORA D40b</name>
		<reportedBy>rpoole@records.media.mit.edu</reportedBy>
		<dateReported>2010-01-23T14:15:00Z</dateReported>
		<adherence>true</adherence>
		<systolic>119</systolic>
		<diastolic>80</diastolic>
		<heartRate>73</heartRate>
	</BloodPressureAdherenceItem>
	<BloodPressureAdherenceItem>
		<name>FORA D40b</name>
		<reportedBy>rpoole@records.media.mit.edu</reportedBy>
		<dateReported>2010-01-24T14:59:00Z</dateReported>
		<adherence>true</adherence>
		<systolic>131</systolic>
		<diastolic>85</diastolic>
		<heartRate>70</heartRate>
	</BloodPressureAdherenceItem>
	<BloodPressureAdherenceItem>
		<name>FORA D40b</name>
		<reportedBy>rpoole@records.media.mit.edu</reportedBy>
		<dateReported>2010-01-25T13:12:00Z</dateReported>
		<adherence>true</adherence>
		<systolic>139</systolic>
		<diastolic>89</diastolic>
		<heartRate>68</heartRate>
	</BloodPressureAdherenceItem>
	<BloodPressureAdherenceItem>
		<name>FORA D40b</name>
		<reportedBy>rpoole@records.media.mit.edu</reportedBy>
		<dateReported>2010-01-26T15:26:00Z</dateReported>
		<adherence>true</adherence>
		<systolic>138</systolic>
		<diastolic>91</diastolic>
		<heartRate>65</heartRate>
	</BloodPressureAdherenceItem>
	<BloodPressureAdherenceItem>
		<name>FORA D40b</name>
		<reportedBy>rpoole@records.media.mit.edu</reportedBy>
		<dateReported>2010-01-27T13:47:00Z</dateReported>
		<adherence>true</adherence>
		<systolic>124</systolic>
		<diastolic>86</diastolic>
		<heartRate>76</heartRate>
	</BloodPressureAdherenceItem>
	<BloodPressureAdherenceItem>
		<name>FORA D40b</name>
		<reportedBy>rpoole@records.media.mit.edu</reportedBy>
		<dateReported>2010-01-28T14:12:00Z</dateReported>
		<adherence>true</adherence>
		<systolic>118</systolic>
		<diastolic>79</diastolic>
		<heartRate>78</heartRate>
	</BloodPressureAdherenceItem>
	<BloodPressureAdherenceItem>
		<name>FORA D40b</name>
		<reportedBy>rpoole@records.media.mit.edu</reportedBy>
		<dateReported>2010-01-29T14:44:00Z</dateReported>
		<adherence>true</adherence>
		<systolic>119</systolic>
		<diastolic>81</diastolic>
		<heartRate>80</heartRate>
	</BloodPressureAdherenceItem>
	<BloodPressureAdherenceItem>
		<name>FORA D40b</name>
		<reportedBy>rpoole@records.media.mit.edu</reportedBy>
		<dateReported>2010-01-30T14:02:00Z</dateReported>
		<adherence>true</adherence>
		<systolic>128</systolic>
		<diastolic>85</diastolic>
		<heartRate>79</heartRate>
	</BloodPressureAdherenceItem>
	<BloodPressureAdherenceItem>
		<name>FORA D40b</name>
		<reportedBy>rpoole@records.media.mit.edu</reportedBy>
		<dateReported>2010-01-31T13:24:00Z</dateReported>
		<adherence>true</adherence>
		<systolic>140</systolic>
		<diastolic>94</diastolic>
		<heartRate>77</heartRate>
	</BloodPressureAdherenceItem>
	<BloodPressureAdherenceItem>
		<name>FORA D40b</name>
		<reportedBy>rpoole@records.media.mit.edu</reportedBy>
		<dateReported>2010-02-01T15:22:00Z</dateReported>
		<adherence>true</adherence>
		<systolic>136</systolic>
		<diastolic>95</diastolic>
		<heartRate>74</heartRate>
	</BloodPressureAdherenceItem>
	<BloodPressureAdherenceItem>
		<name>FORA D40b</name>
		<reportedBy>rpoole@records.media.mit.edu</reportedBy>
		<dateReported>2010-02-02T15:00:00Z</dateReported>
		<adherence>true</adherence>
		<systolic>122</systolic>
		<diastolic>84</diastolic>
		<heartRate>78</heartRate>
	</BloodPressureAdherenceItem>
	<BloodPressureAdherenceItem>
		<name>FORA D40b</name>
		<reportedBy>rpoole@records.media.mit.edu</reportedBy>
		<dateReported>2010-02-03T13:53:00Z</dateReported>
		<adherence>true</adherence>
		<systolic>118</systolic>
		<diastolic>76</diastolic>
		<heartRate>82</heartRate>
	</BloodPressureAdherenceItem>
	<BloodPressureAdherenceItem>
		<name>FORA D40b</name>
		<reportedBy>rpoole@records.media.mit.edu</reportedBy>
		<dateReported>2010-02-04T14:00:00Z</dateReported>
		<adherence>true</adherence>
		<systolic>117</systolic>
		<diastolic>78</diastolic>
		<heartRate>81</heartRate>
	</BloodPressureAdherenceItem>
	<BloodPressureAdherenceItem>
		<name>FORA D40b</name>
		<reportedBy>rpoole@records.media.mit.edu</reportedBy>
		<dateReported>2010-02-05T13:54:00Z</dateReported>
		<adherence>true</adherence>
		<systolic>138</systolic>
		<diastolic>89</diastolic>
		<heartRate>80</heartRate>
	</BloodPressureAdherenceItem>
	<BloodPressureAdherenceItem>
		<name>FORA D40b</name>
		<reportedBy>rpoole@records.media.mit.edu</reportedBy>
		<dateReported>2010-02-06T13:14:00Z</dateReported>
		<adherence>true</adherence>
		<systolic>147</systolic>
		<diastolic>92</diastolic>
		<heartRate>75</heartRate>
	</BloodPressureAdherenceItem>
	<BloodPressureAdherenceItem>
		<name>FORA D40b</name>
		<reportedBy>rpoole@records.media.mit.edu</reportedBy>
		<dateReported>2010-02-07T13:00:00Z</dateReported>
		<adherence>true</adherence>
		<systolic>152</systolic>
		<diastolic>96</diastolic>
		<heartRate>70</heartRate>
	</BloodPressureAdherenceItem>
	<BloodPressureAdherenceItem>
		<name>FORA D40b</name>
		<reportedBy>rpoole@records.media.mit.edu</reportedBy>
		<dateReported>2010-02-08T13:10:00Z</dateReported>
		<adherence>true</adherence>
		<systolic>157</systolic>
		<diastolic>99</diastolic>
		<heartRate>71</heartRate>
	</BloodPressureAdherenceItem>
	<BloodPressureAdherenceItem>
		<name>FORA D40b</name>
		<reportedBy>rpoole@records.media.mit.edu</reportedBy>
		<dateReported>2010-02-09T13:18:00Z</dateReported>
		<adherence>true</adherence>
		<systolic>141</systolic>
		<diastolic>94</diastolic>
		<heartRate>70</heartRate>
	</BloodPressureAdherenceItem>
	<BloodPressureAdherenceItem>
		<name>FORA D40b</name>
		<reportedBy>rpoole@records.media.mit.edu</reportedBy>
		<dateReported>2010-02-10T13:29:00Z</dateReported>
		<adherence>true</adherence>
		<systolic>134</systolic>
		<diastolic>85</diastolic>
		<heartRate>73</heartRate>
	</BloodPressureAdherenceItem>
	<BloodPressureAdherenceItem>
		<name>FORA D40b</name>
		<reportedBy>rpoole@records.media.mit.edu</reportedBy>
		<dateReported>2010-02-11T13:40:00Z</dateReported>
		<adherence>true</adherence>
		<systolic>122</systolic>
		<diastolic>82</diastolic>
		<heartRate>75</heartRate>
	</BloodPressureAdherenceItem>
	<BloodPressureAdherenceItem>
		<name>FORA D40b</name>
		<reportedBy>rpoole@records.media.mit.edu</reportedBy>
		<dateReported>2010-02-12T13:51:00Z</dateReported>
		<adherence>true</adherence>
		<systolic>118</systolic>
		<diastolic>78</diastolic>
		<heartRate>76</heartRate>
	</BloodPressureAdherenceItem>
</IndivoDocuments>